MANIFEST.in
README.rst
setup.py
hemvfunniest/__init__.py
hemvfunniest/text.py
hemvfunniest.egg-info/PKG-INFO
hemvfunniest.egg-info/SOURCES.txt
hemvfunniest.egg-info/dependency_links.txt
hemvfunniest.egg-info/not-zip-safe
hemvfunniest.egg-info/requires.txt
hemvfunniest.egg-info/top_level.txt