Metadata-Version: 1.0
Name: hemvfunniest
Version: 0.0.3
Summary: The funniest joke in the world
Home-page: https://bitbucket.org/hemv/hemv_funniest.git
Author: hemv
Author-email: vichet.hem@gmail.com
License: MIT
Platform: UNKNOWN
